setup.py
kilometer/__init__.py
kilometer.egg-info/PKG-INFO
kilometer.egg-info/SOURCES.txt
kilometer.egg-info/dependency_links.txt
kilometer.egg-info/requires.txt
kilometer.egg-info/top_level.txt
test/__init__.py
test/integration.py