Metadata-Version: 1.1
Name: kilometer
Version: 1.0.1
Summary: The official Kilometer.io library for Python
Home-page: https://github.com/kilometer-io/kilometer-python
Author: Kilometer.io Ltd.
Author-email: info@kilometer.io
License: Apache
Keywords: kilometer analytics
Platform: UNKNOWN
Classifier: License :: OSI Approved :: Apache Software License
Classifier: Operating System :: OS Independent
Classifier: Programming Language :: Python :: 2
Classifier: Programming Language :: Python :: 3
